django_mysql_utf8mb4/__init__.py
django_mysql_utf8mb4/admin.py
django_mysql_utf8mb4/apps.py
django_mysql_utf8mb4/checks.py
django_mysql_utf8mb4/migrate.py
django_mysql_utf8mb4/models.py
django_mysql_utf8mb4/tests.py
django_mysql_utf8mb4/views.py
django_mysql_utf8mb4/management/__init__.py
django_mysql_utf8mb4/management/commands/__init__.py
django_mysql_utf8mb4/management/commands/migrate_collation.py
django_mysql_utf8mb4/migrations/0001_utf8mb4.py
django_mysql_utf8mb4/migrations/__init__.py
django_mysql_utf8mb4-0.1.7.dist-info/LICENSE
django_mysql_utf8mb4-0.1.7.dist-info/METADATA
django_mysql_utf8mb4-0.1.7.dist-info/WHEEL
django_mysql_utf8mb4-0.1.7.dist-info/top_level.txt
django_mysql_utf8mb4-0.1.7.dist-info/RECORD
